arithmetic/__init__.py
arithmetic/operations.py
arithmetic_package-0.1.dist-info/LICENSE
arithmetic_package-0.1.dist-info/METADATA
arithmetic_package-0.1.dist-info/WHEEL
arithmetic_package-0.1.dist-info/top_level.txt
arithmetic_package-0.1.dist-info/RECORD
