Metadata-Version: 2.1
Name: arithmetic-package
Version: 0.1
Summary: A simple package for basic arithmetic operations using functions
Home-page: https://github.com/yourusername/arithmetic-package
Author: Your Name
Author-email: your.email@example.com
License: MIT
Platform: UNKNOWN
Classifier: Programming Language :: Python :: 3
Classifier: License :: OSI Approved :: MIT License
Classifier: Operating System :: OS Independent
Requires-Python: >=3.6
